.project
.pydevproject
setup.py
.settings/org.eclipse.ltk.core.refactoring.prefs
src-test/sip/__init__.py
src-test/sip/testdecorator.py
src-test/sip/testproxy.py
src-test/sip/testsipclient.py
src/PyAliSip.egg-info/PKG-INFO
src/PyAliSip.egg-info/SOURCES.txt
src/PyAliSip.egg-info/dependency_links.txt
src/PyAliSip.egg-info/top_level.txt
src/sip/__init__.py
src/sip/decorator.py
src/sip/proxy.py
src/sip/sipclient.py