Metadata-Version: 1.0
Name: PyAliSip
Version: 0.2
Summary: This is an taobao.com SIP client
Home-page: http://packages.python.org/PyAliSip
Author: shaomq
Author-email: shaomq@gmail.com
License: PSF
Keywords: taobao sip
Platform: UNKNOWN
